{
  "expect": {
    "name": "Đào Thuý Nga",
    "email": "thuyngadao22@gmail.com",
    "phone": "0865034796",
    "date": "",
    "location": "Triều Khúc Thanh Xuân Hà Nội Nhật Bản",
    "organization": "Học viện Kỹ thuật Mật mã",
    "gender": "Nữ"
  },
  "result": {
    "name": "Đào Thuý Nga",
    "email": "thuyngadao22@gmail.com",
    "phone": "0865034796",
    "date": "",
    "location": "Triều Khúc Thanh Xuân Hà Nội Nhật Bản",
    "organization": "Học viện Kỹ thuật Mật mã",
    "gender": "Nữ"
  },
  "accuracy": "100%",
  "language": "Vietnamese"
}

